tronwebwpy/__init__.py
tronwebwpy/main.py
tronwebwpy-0.0.1.dist-info/licenses/LICENSE.txt
tronwebwpy-0.0.1.dist-info/METADATA
tronwebwpy-0.0.1.dist-info/WHEEL
tronwebwpy-0.0.1.dist-info/top_level.txt
tronwebwpy-0.0.1.dist-info/RECORD
