Metadata-Version: 2.4
Name: tronwebwpy
Version: 0.0.1
Summary: tronwebwpy library for Python
Author: dianatron
Author-email:  talavac987@evoxury.com
License: MIT
Project-URL: Source Repository, https://github.com
License-File: LICENSE.txt
Requires-Dist: requests
Dynamic: author
Dynamic: author-email
Dynamic: description
Dynamic: description-content-type
Dynamic: license
Dynamic: license-file
Dynamic: project-url
Dynamic: requires-dist
Dynamic: summary
